repoze.sendmail-4.4-py2.7-nspkg.pth
repoze/sendmail/__init__.py
repoze/sendmail/_compat.py
repoze/sendmail/delivery.py
repoze/sendmail/encoding.py
repoze/sendmail/interfaces.py
repoze/sendmail/maildir.py
repoze/sendmail/mailer.py
repoze/sendmail/queue.py
repoze/sendmail/tests/__init__.py
repoze/sendmail/tests/mail.zcml
repoze/sendmail/tests/test_delivery.py
repoze/sendmail/tests/test_encoding.py
repoze/sendmail/tests/test_maildir.py
repoze/sendmail/tests/test_mailer.py
repoze/sendmail/tests/test_queue.py
repoze/sendmail/tests/test_transaction.py
repoze.sendmail-4.4.dist-info/DESCRIPTION.rst
repoze.sendmail-4.4.dist-info/METADATA
repoze.sendmail-4.4.dist-info/RECORD
repoze.sendmail-4.4.dist-info/WHEEL
repoze.sendmail-4.4.dist-info/entry_points.txt
repoze.sendmail-4.4.dist-info/metadata.json
repoze.sendmail-4.4.dist-info/namespace_packages.txt
repoze.sendmail-4.4.dist-info/top_level.txt
