Metadata-Version: 2.0
Name: repoze.sendmail
Version: 4.4
Summary: Repoze Sendmail
Home-page: http://www.repoze.org
Author: Chris Rossi
Author-email: repoze-dev@lists.repoze.org
License: ZPL 2.1
Platform: UNKNOWN
Classifier: Development Status :: 5 - Production/Stable
Classifier: Intended Audience :: Developers
Classifier: Programming Language :: Python
Classifier: Programming Language :: Python :: 2
Classifier: Programming Language :: Python :: 2.7
Classifier: Programming Language :: Python :: 3
Classifier: Programming Language :: Python :: 3.4
Classifier: Programming Language :: Python :: 3.5
Classifier: Programming Language :: Python :: 3.6
Classifier: Programming Language :: Python :: Implementation :: CPython
Classifier: Programming Language :: Python :: Implementation :: PyPy
Requires-Dist: setuptools
Requires-Dist: transaction
Requires-Dist: zope.interface (>=3.6.0)
Provides-Extra: docs
Requires-Dist: Sphinx; extra == 'docs'
Requires-Dist: repoze.sphinx.autointerface; extra == 'docs'
Requires-Dist: setuptools; extra == 'docs'
Requires-Dist: transaction; extra == 'docs'
Requires-Dist: zope.interface (>=3.6.0); extra == 'docs'
Provides-Extra: testing
Requires-Dist: coverage; extra == 'testing'
Requires-Dist: nose; extra == 'testing'
Requires-Dist: setuptools; extra == 'testing'
Requires-Dist: transaction; extra == 'testing'
Requires-Dist: zope.interface (>=3.6.0); extra == 'testing'
